rgbloom/__init__.py
rgbloom/__main__.py
rgbloom/choices_mag_plot.py
rgbloom/version.py
rgbloom/core/__init__.py
rgbloom/core/step1.py
rgbloom/core/step2.py
rgbloom/core/step3.py
rgbloom/core/step4.py
rgbloom/core/step5.py
rgbloom/gui/__init__.py
rgbloom/gui/step6.py
rgbloom/gui/style.py
rgbloom-2.0.dist-info/LICENSE
rgbloom-2.0.dist-info/METADATA
rgbloom-2.0.dist-info/WHEEL
rgbloom-2.0.dist-info/entry_points.txt
rgbloom-2.0.dist-info/top_level.txt
rgbloom-2.0.dist-info/RECORD
